AUTHORS.rst
CONTRIBUTING.rst
HISTORY.rst
LICENSE
MANIFEST.in
README.rst
setup.cfg
setup.py
dadrin_pyutils/__init__.py
dadrin_pyutils/date_utils.py
dadrin_pyutils/ga_utils.py
dadrin_pyutils/gs_utils.py
dadrin_pyutils/mongo_utils.py
dadrin_pyutils.egg-info/PKG-INFO
dadrin_pyutils.egg-info/SOURCES.txt
dadrin_pyutils.egg-info/dependency_links.txt
dadrin_pyutils.egg-info/not-zip-safe
dadrin_pyutils.egg-info/top_level.txt
docs/Makefile
docs/authors.rst
docs/conf.py
docs/contributing.rst
docs/history.rst
docs/index.rst
docs/installation.rst
docs/make.bat
docs/readme.rst
docs/usage.rst
tests/__init__.py
tests/test_date_utils.py
tests/test_ga_utils.py
tests/test_gs_utils.py
tests/test_mongo_utils.py