Metadata-Version: 1.1
Name: dadrin-pyutils
Version: 0.1.0
Summary: Python utilities for data driven proejcts
Home-page: https://github.com/lluiscanet/dadrin_pyutils
Author: Lluis Canet
Author-email: lluis.canet@dadrin.com
License: BSD
Keywords: dadrin_pyutils
Platform: UNKNOWN
Classifier: Development Status :: 2 - Pre-Alpha
Classifier: Intended Audience :: Developers
Classifier: License :: OSI Approved :: BSD License
Classifier: Natural Language :: English
Classifier: Programming Language :: Python :: 2
Classifier: Programming Language :: Python :: 2.6
Classifier: Programming Language :: Python :: 2.7
Classifier: Programming Language :: Python :: 3
Classifier: Programming Language :: Python :: 3.3
Classifier: Programming Language :: Python :: 3.4
